watson_transformer/__init__.py
watson_transformer/flat_column_transformer.py
watson_transformer/json_transformer.py
watson_transformer/watson_service_transformer.py
watson_transformer/contrib/__init__.py
watson_transformer/contrib/readers.py
watson_transformer/contrib/response_base.py
watson_transformer/contrib/nlu/__init__.py
watson_transformer/contrib/nlu/default_nlu_parser.py
watson_transformer/contrib/stt/__init__.py
watson_transformer/contrib/stt/default_stt_parser.py
watson_transformer/service/__init__.py
watson_transformer/service/nlu.py
watson_transformer/service/service_base.py
watson_transformer/service/stt.py
watson_transformer-0.0.17.dist-info/METADATA
watson_transformer-0.0.17.dist-info/WHEEL
watson_transformer-0.0.17.dist-info/top_level.txt
watson_transformer-0.0.17.dist-info/zip-safe
watson_transformer-0.0.17.dist-info/RECORD
